mies/__init__.py
mies/parameters.py
mies/simulation.py
mies/econtools/__init__.py
mies/econtools/budget.py
mies/econtools/hicks.py
mies/econtools/slutsky.py
mies/econtools/utility.py
mies/entities/__init__.py
mies/entities/bank.py
mies/entities/broker.py
mies/entities/god.py
mies/entities/insurer.py
mies/entities/person.py
mies-0.0.0.dist-info/LICENSE
mies-0.0.0.dist-info/METADATA
mies-0.0.0.dist-info/WHEEL
mies-0.0.0.dist-info/top_level.txt
mies-0.0.0.dist-info/RECORD
