Metadata-Version: 2.1
Name: mies
Version: 0.0.0
Summary: Miniature Insurance Economic Simulator
Home-page: https://github.com/genedan/MIES
Author: Gene Dan
Author-email: genedan@gmail.com
License: UNKNOWN
Platform: UNKNOWN
Classifier: Programming Language :: Python :: 3.8
Classifier: License :: OSI Approved :: GNU General Public License v3 (GPLv3)
Classifier: Operating System :: POSIX :: Linux
Requires-Python: >=3.8.2
